buct_course/__init__.py
buct_course/auth.py
buct_course/client.py
buct_course/client_optimized.py
buct_course/course_utils.py
buct_course/exceptions.py
buct_course/lid_utils.py
buct_course/test_utils.py
buct_course-1.2.0.dist-info/licenses/LICENSE
example/README.py
example/demo_client.py
example/example1_basic_usage.py
example/example2_detailed_homework.py
example/example3_time_analysis.py
example/example4_homework_tasks.py
example/example5_test_management.py
example/full_html_test.py
example/homework_example.py
example/lid_type_test.py
example/simple_test.py
example/subject_test.py
example/test_example.py
example/time_test.py
example/updated_utils_test.py
test/buct_course_test_main.py
test/quick_test.py
test/simple_test.py
test/test_client.py
test/test_delay_improvements.py
test/test_diagnosis.py
buct_course-1.2.0.dist-info/METADATA
buct_course-1.2.0.dist-info/WHEEL
buct_course-1.2.0.dist-info/top_level.txt
buct_course-1.2.0.dist-info/RECORD
