Metadata-Version: 2.4
Name: buct-course
Version: 1.2.0
Summary: 北京化工大学课程平台作业查询
Home-page: https://github.com/Ling0727-ai/python-buct-course
Author: LingXin07
Author-email: LingXin07 <ling1163840260@gmail.com>
License: MIT
Project-URL: Homepage, https://github.com/Ling0727-ai/python-buct-course
Keywords: buct,education,api,automation
Classifier: Development Status :: 3 - Alpha
Classifier: Intended Audience :: Education
Classifier: License :: OSI Approved :: MIT License
Classifier: Programming Language :: Python :: 3
Classifier: Programming Language :: Python :: 3.12
Classifier: Programming Language :: Python :: 3.13
Requires-Python: >=3.12
License-File: LICENSE
Requires-Dist: requests>=2.25.0
Requires-Dist: beautifulsoup4>=4.9.0
Dynamic: author
Dynamic: home-page
Dynamic: license-file
Dynamic: requires-python
